odoo/addons/pos_product_multi_barcode/README.rst
odoo/addons/pos_product_multi_barcode/__init__.py
odoo/addons/pos_product_multi_barcode/__manifest__.py
odoo/addons/pos_product_multi_barcode/i18n/es.po
odoo/addons/pos_product_multi_barcode/i18n/it.po
odoo/addons/pos_product_multi_barcode/i18n/pos_product_multi_barcode.pot
odoo/addons/pos_product_multi_barcode/models/__init__.py
odoo/addons/pos_product_multi_barcode/models/pos_session.py
odoo/addons/pos_product_multi_barcode/models/product.py
odoo/addons/pos_product_multi_barcode/readme/CONTRIBUTORS.rst
odoo/addons/pos_product_multi_barcode/readme/CREDITS.rst
odoo/addons/pos_product_multi_barcode/readme/DESCRIPTION.rst
odoo/addons/pos_product_multi_barcode/static/description/icon.png
odoo/addons/pos_product_multi_barcode/static/description/index.html
odoo/addons/pos_product_multi_barcode/static/src/js/db.js
odoo_addon_pos_product_multi_barcode-16.0.1.0.2.dist-info/METADATA
odoo_addon_pos_product_multi_barcode-16.0.1.0.2.dist-info/WHEEL
odoo_addon_pos_product_multi_barcode-16.0.1.0.2.dist-info/top_level.txt
odoo_addon_pos_product_multi_barcode-16.0.1.0.2.dist-info/RECORD
