Metadata-Version: 2.1
Name: odoo-addon-pos_product_multi_barcode
Version: 16.0.1.0.2
Summary: Make product multi barcodes usable in the point of sale
Home-page: https://github.com/OCA/pos
Author: Akretion, Odoo Community Association (OCA)
Author-email: support@odoo-community.org
License: AGPL-3
Classifier: Programming Language :: Python
Classifier: Framework :: Odoo
Classifier: Framework :: Odoo :: 16.0
Classifier: License :: OSI Approved :: GNU Affero General Public License v3
Requires-Python: >=3.10
Requires-Dist: odoo-addon-product-multi-barcode<16.1dev,>=16.0dev
Requires-Dist: odoo<16.1dev,>=16.0a
